{ "frames": {
   "0": {
    "frame": { "x": 1, "y": 1, "w": 802, "h": 592 },
    "rotated": false,
    "trimmed": false,
    "spriteSourceSize": { "x": 0, "y": 0, "w": 800, "h": 590 },
    "sourceSize": { "w": 800, "h": 590 },
    "duration": 100
   },
   "1": {
    "frame": { "x": 804, "y": 1, "w": 802, "h": 592 },
    "rotated": false,
    "trimmed": false,
    "spriteSourceSize": { "x": 0, "y": 0, "w": 800, "h": 590 },
    "sourceSize": { "w": 800, "h": 590 },
    "duration": 100
   }
 },
 "meta": {
  "app": "http://www.aseprite.org/",
  "version": "1.2.21-dev",
  "image": "Scenario6_Boy+Dog1-sheet.png",
  "format": "RGBA8888",
  "size": { "w": 1607, "h": 594 },
  "scale": "1",
  "frameTags": [
   { "name": "Tag", "from": 0, "to": 1, "direction": "forward" }
  ],
  "layers": [
   { "name": "Layer", "opacity": 255, "blendMode": "normal" }
  ],
  "slices": [
  ]
 }
}
